mypackage/EFunction.py
mypackage/__init__.py
efunction-0.0.10.dist-info/METADATA
efunction-0.0.10.dist-info/WHEEL
efunction-0.0.10.dist-info/top_level.txt
efunction-0.0.10.dist-info/RECORD
