Metadata-Version: 2.1
Name: efunction
Version: 0.0.10
Summary: efunction Python data analysis
Home-page: UNKNOWN
Author: 疯狂的Hi Excel & Python
Author-email: EFunction2020@163.com
License: UNKNOWN
Platform: UNKNOWN
